exception_reports/__init__.py
exception_reports/decorators.py
exception_reports/logs.py
exception_reports/report_template.html
exception_reports/reporter.py
exception_reports/storages.py
exception_reports/traceback.py
exception_reports/utils.py
exception_reports-2.0.0.dist-info/LICENSE
exception_reports-2.0.0.dist-info/METADATA
exception_reports-2.0.0.dist-info/WHEEL
exception_reports-2.0.0.dist-info/top_level.txt
exception_reports-2.0.0.dist-info/RECORD
