Metadata-Version: 2.1
Name: exception-reports
Version: 2.0.0
Summary: Interactive stacktraces with variable state at each level.
Home-page: https://github.com/brycedrennan/exception-reports
Download-URL: https://github.com/brycedrennan/exception-reports/tarball/2.0.0
Author: Bryce Drennan
Author-email: exception_reports@brycedrennan.org
Keywords: exception handler,exceptions,error logs
Requires-Python: >=3.8
License-File: LICENSE
Requires-Dist: jinja2 (>=2.4)
Requires-Dist: decorator (>=4.1)
